// class version 52.0 (52)
// access flags 0x21
public class cn/itcast/jvm/Test1 {

  // compiled from: Test1.java

  // access flags 0x1
  public <init>()V
   L0
    LINENUMBER 3 L0
    ALOAD 0
    INVOKESPECIAL java/lang/Object.<init> ()V
    RETURN
    MAXSTACK = 1
    MAXLOCALS = 1

  // access flags 0x1
  public add()I
   L0
    LINENUMBER 6 L0
    //把一压入栈
    ICONST_1
    // 放到局部变量表
    ISTORE 1
   L1
    LINENUMBER 7 L1
    ICONST_2
    ISTORE 2
   L2
    LINENUMBER 8 L2
    ILOAD 1
    ILOAD 2
    IADD
    ISTORE 3
   L3
    LINENUMBER 9 L3
    ILOAD 3
    IRETURN
    MAXSTACK = 2
    MAXLOCALS = 4

  // access flags 0x9
  public static main([Ljava/lang/String;)V
   L0
    LINENUMBER 13 L0
    NEW cn/itcast/jvm/Test1
    DUP
    INVOKESPECIAL cn/itcast/jvm/Test1.<init> ()V
    ASTORE 1
   L1
    LINENUMBER 14 L1
    ALOAD 1
    INVOKEVIRTUAL cn/itcast/jvm/Test1.add ()I
    ISTORE 2
   L2
    LINENUMBER 15 L2
    GETSTATIC java/lang/System.out : Ljava/io/PrintStream;
    ILOAD 2
    INVOKEVIRTUAL java/io/PrintStream.println (I)V
   L3
    LINENUMBER 16 L3
    RETURN
    MAXSTACK = 2
    MAXLOCALS = 3
}
